autobackuper.py
autobackuper-1.0.0.dist-info/LICENSE
autobackuper-1.0.0.dist-info/METADATA
autobackuper-1.0.0.dist-info/WHEEL
autobackuper-1.0.0.dist-info/entry_points.txt
autobackuper-1.0.0.dist-info/top_level.txt
autobackuper-1.0.0.dist-info/RECORD
