Metadata-Version: 2.1
Name: autobackuper
Version: 1.0.0
Summary: Automatic tool to backup a file to git
Home-page: https://github.com/maksloboda/AutoBackuper
Author: MaksL
Author-email: contactmaksloboda@gmail.com
License: UNKNOWN
Project-URL: Bug Tracker, https://github.com/maksloboda/AutoBackuper/issues
Platform: UNKNOWN
Classifier: Programming Language :: Python :: 3
Classifier: License :: OSI Approved :: GNU General Public License v3 (GPLv3)
Classifier: Operating System :: OS Independent
Requires-Python: >=3.6
License-File: LICENSE
Requires-Dist: click
